client/__init__.py
client/main.py
client/tools.py
dbt_mcp/__init__.py
dbt_mcp/main.py
dbt_mcp/py.typed
dbt_mcp/config/config.py
dbt_mcp/dbt_admin/client.py
dbt_mcp/dbt_admin/tools.py
dbt_mcp/dbt_cli/binary_type.py
dbt_mcp/dbt_cli/tools.py
dbt_mcp/discovery/client.py
dbt_mcp/discovery/tools.py
dbt_mcp/gql/errors.py
dbt_mcp/mcp/create.py
dbt_mcp/mcp/server.py
dbt_mcp/oauth/dbt_platform.py
dbt_mcp/oauth/fastapi_app.py
dbt_mcp/oauth/logging.py
dbt_mcp/oauth/login.py
dbt_mcp/oauth/token.py
dbt_mcp/prompts/__init__.py
dbt_mcp/prompts/prompts.py
dbt_mcp/semantic_layer/client.py
dbt_mcp/semantic_layer/levenshtein.py
dbt_mcp/semantic_layer/tools.py
dbt_mcp/semantic_layer/types.py
dbt_mcp/semantic_layer/gql/gql.py
dbt_mcp/semantic_layer/gql/gql_request.py
dbt_mcp/sql/tools.py
dbt_mcp/tools/annotations.py
dbt_mcp/tools/definitions.py
dbt_mcp/tools/policy.py
dbt_mcp/tools/register.py
dbt_mcp/tools/tool_names.py
dbt_mcp/tools/toolsets.py
dbt_mcp/tracking/tracking.py
mseep_dbt_mcp-0.0.0.dist-info/licenses/LICENSE
remote_mcp/__init__.py
remote_mcp/session.py
mseep_dbt_mcp-0.0.0.dist-info/METADATA
mseep_dbt_mcp-0.0.0.dist-info/WHEEL
mseep_dbt_mcp-0.0.0.dist-info/entry_points.txt
mseep_dbt_mcp-0.0.0.dist-info/top_level.txt
mseep_dbt_mcp-0.0.0.dist-info/RECORD
