Metadata-Version: 2.4
Name: mseep-dbt-mcp
Version: 0.0.0
Summary: A MCP (Model Context Protocol) server for interacting with dbt resources.
Author-email: mseep <support@skydeck.ai>
License:                                  Apache License
Project-URL: Documentation, https://github.com/dbt-labs/dbt-mcp#readme
Project-URL: Issues, https://github.com/dbt-labs/dbt-mcp/issues
Project-URL: Source, https://github.com/dbt-labs/dbt-mcp
Project-URL: Changelog, https://github.com/dbt-labs/dbt-mcp/blob/main/CHANGELOG.md
Classifier: License :: OSI Approved :: Apache Software License
Classifier: Programming Language :: Python :: 3
Classifier: Operating System :: OS Independent
Classifier: Development Status :: 4 - Beta
Classifier: Intended Audience :: Developers
Requires-Python: >=3.12
License-File: LICENSE
Requires-Dist: authlib==1.6.3
Requires-Dist: dbt-protos==1.0.317
Requires-Dist: dbt-sl-sdk[sync]==0.13.0
Requires-Dist: dbtlabs-vortex==0.2.0
Requires-Dist: fastapi==0.116.1
Requires-Dist: uvicorn==0.30.6
Requires-Dist: mcp[cli]==1.10.1
Requires-Dist: pandas==2.2.3
Requires-Dist: pydantic-settings==2.10.1
Requires-Dist: pyjwt==2.10.1
Requires-Dist: pyyaml==6.0.2
Requires-Dist: requests==2.32.4
Dynamic: license-file
